django-gnupy/__init__.py
django-gnupy/test.py
example/__init__.py
example/asgi.py
example/settings.py
example/urls.py
example/wsgi.py
django_gnupy-0.1.dist-info/METADATA
django_gnupy-0.1.dist-info/WHEEL
django_gnupy-0.1.dist-info/top_level.txt
django_gnupy-0.1.dist-info/RECORD
